cleanmymac/__init__.py
cleanmymac/__init__.pyc
cleanmymac/__version__.py
cleanmymac/__version__.pyc
cleanmymac/cli.py
cleanmymac/colors.py
cleanmymac/constants.py
cleanmymac/constants.pyc
cleanmymac/log.py
cleanmymac/log.pyc
cleanmymac/registry.py
cleanmymac/registry.pyc
cleanmymac/schema.py
cleanmymac/schema.pyc
cleanmymac/target.py
cleanmymac/target.pyc
cleanmymac/util.py
cleanmymac/util.pyc
cleanmymac/__pycache__/__init__.cpython-35.pyc
cleanmymac/__pycache__/__version__.cpython-35.pyc
cleanmymac/__pycache__/constants.cpython-35.pyc
cleanmymac/__pycache__/log.cpython-35.pyc
cleanmymac/__pycache__/registry.cpython-35.pyc
cleanmymac/__pycache__/schema.cpython-35.pyc
cleanmymac/__pycache__/target.cpython-35.pyc
cleanmymac/__pycache__/util.cpython-35.pyc
cleanmymac/builtins/__init__.py
cleanmymac/builtins/__init__.pyc
cleanmymac/builtins/anaconda.yaml
cleanmymac/builtins/homebrew.yaml
cleanmymac/builtins/jdk.yaml
cleanmymac/builtins/mactex.yaml
cleanmymac/builtins/texlive.yaml
cleanmymac/builtins/trash.yaml
cleanmymac/builtins/__pycache__/__init__.cpython-35.pyc
cleanmymac/test/__init__.py
cleanmymac/test/__init__.pyc
cleanmymac/test/test_schema.py
cleanmymac/test/test_util.py
cleanmymac/test/__pycache__/__init__.cpython-35.pyc
cleanmymac/test/__pycache__/test_schema.cpython-26-PYTEST.pyc
cleanmymac/test/__pycache__/test_schema.cpython-27-PYTEST.pyc
cleanmymac/test/__pycache__/test_schema.cpython-35-PYTEST.pyc
cleanmymac/test/__pycache__/test_schema.pypy-27-PYTEST.pyc
cleanmymac/test/__pycache__/test_util.cpython-26-PYTEST.pyc
cleanmymac/test/__pycache__/test_util.cpython-27-PYTEST.pyc
cleanmymac/test/__pycache__/test_util.cpython-35-PYTEST.pyc
cleanmymac/test/__pycache__/test_util.pypy-27-PYTEST.pyc
cleanmymac-0.1.17.dist-info/DESCRIPTION.rst
cleanmymac-0.1.17.dist-info/METADATA
cleanmymac-0.1.17.dist-info/RECORD
cleanmymac-0.1.17.dist-info/WHEEL
cleanmymac-0.1.17.dist-info/entry_points.txt
cleanmymac-0.1.17.dist-info/metadata.json
cleanmymac-0.1.17.dist-info/top_level.txt
