Metadata-Version: 2.0
Name: cleanmymac
Version: 0.1.17
Summary: A simple utility to clean your mac of old stuff
Home-page: https://github.com/cosminbasca/cleanmymac
Author: Cosmin Basca
Author-email: cosmin.basca@gmail.com
License: Apache
Platform: MacOS
Classifier: Development Status :: 4 - Beta
Classifier: Intended Audience :: End Users/Desktop
Classifier: License :: OSI Approved :: Apache Software License
Classifier: Natural Language :: English
Classifier: Operating System :: MacOS
Classifier: Programming Language :: Python
Classifier: Programming Language :: Python :: 2.6
Classifier: Programming Language :: Python :: 2.7
Classifier: Programming Language :: Python :: 3.5
Classifier: Programming Language :: Python :: Implementation :: PyPy
Classifier: Topic :: Text Processing :: Markup
Classifier: Topic :: Utilities
Requires-Dist: click (>=6.2)
Requires-Dist: click-log (>=0.1.3)
Requires-Dist: colorlog (>=2.6.0)
Requires-Dist: natsort (>=4.0.4)
Requires-Dist: pytest (>=2.8.7)
Requires-Dist: pyyaml (>=3.11)
Requires-Dist: sarge (>=0.1.4)
Requires-Dist: six (>=1.10.0)
Requires-Dist: tabulate (>=0.7.5)
Requires-Dist: voluptuous (>=0.8.8)
